README.md
setup.cfg
setup.py
kiss_cache/__init__.py
kiss_cache/cache.py
kiss_cache/test_cache.py
kiss_cache.egg-info/PKG-INFO
kiss_cache.egg-info/SOURCES.txt
kiss_cache.egg-info/dependency_links.txt
kiss_cache.egg-info/top_level.txt
kiss_cache/stores/__init__.py
kiss_cache/stores/django_cache.py
kiss_cache/stores/in_memory.py