Metadata-Version: 1.1
Name: kiss-cache
Version: 0.6.0
Summary: "Keep It Simple Stupid" Cache
Home-page: https://github.com/HiveTraum/kiss_cache
Author: Bergutov Ruslan
Author-email: ruslanbergutov@gmail.com
License: MIT
Download-URL: https://github.com/HiveTraum/kiss_cache/archive/0.5.9.tar.gz
Keywords: cache,memoize,kiss
Platform: UNKNOWN
Classifier: Development Status :: 4 - Beta
Classifier: Intended Audience :: Developers
Classifier: License :: OSI Approved :: MIT License
Classifier: Programming Language :: Python :: 3.5
Classifier: Programming Language :: Python :: 3.6
Classifier: Programming Language :: Python :: 3.7
